latexmlsuite/__init__.py
latexmlsuite/main_suite.py
latexmlsuite-0.4.1.dist-info/LICENSE.txt
latexmlsuite-0.4.1.dist-info/METADATA
latexmlsuite-0.4.1.dist-info/WHEEL
latexmlsuite-0.4.1.dist-info/entry_points.txt
latexmlsuite-0.4.1.dist-info/top_level.txt
latexmlsuite-0.4.1.dist-info/RECORD
